LICENSE
MANIFEST.in
README.md
pyproject.toml
setup.cfg
pynsd.egg-info/PKG-INFO
pynsd.egg-info/SOURCES.txt
pynsd.egg-info/dependency_links.txt
pynsd.egg-info/not-zip-safe
pynsd.egg-info/top_level.txt
src/pynsd/VERSION
src/pynsd/__init__.py
src/pynsd/client.py
src/pynsd/exception.py
src/pynsd/parser.py
tests/test_client.py