Metadata-Version: 2.4
Name: pynsd
Version: 0.1.2.2
Summary: Library to connect and call command against new NSD >=4 control api.
Author-email: greenSec GmbH <meinecke@greensec.de>
License-Expression: Apache-2.0
Project-URL: Homepage, https://github.com/greensec/pynsd
Project-URL: Documentation, https://github.com/greensec/pynsd#readme
Project-URL: Changelog, https://github.com/greensec/pynsd/releases
Project-URL: Issues, https://github.com/greensec/pynsd/issues
Project-URL: Source, https://github.com/greensec/pynsd
Keywords: nsd,api
Classifier: Programming Language :: Python :: 3
Classifier: Operating System :: OS Independent
Classifier: Topic :: Software Development
Requires-Python: >=3.6
License-File: LICENSE
Dynamic: license-file
